safeeyes/__init__.py
safeeyes/__main__.py
safeeyes/context.py
safeeyes/core.py
safeeyes/model.py
safeeyes/plugin_manager.py
safeeyes/safeeyes.py
safeeyes/translations.py
safeeyes/utility.py
safeeyes/config/safeeyes.json
safeeyes/config/locale/safeeyes.pot
safeeyes/config/locale/ar/LC_MESSAGES/safeeyes.mo
safeeyes/config/locale/ar/LC_MESSAGES/safeeyes.po
safeeyes/config/locale/bg/LC_MESSAGES/safeeyes.mo
safeeyes/config/locale/bg/LC_MESSAGES/safeeyes.po
safeeyes/config/locale/bn/LC_MESSAGES/safeeyes.mo
safeeyes/config/locale/bn/LC_MESSAGES/safeeyes.po
safeeyes/config/locale/bn_IN/LC_MESSAGES/safeeyes.mo
safeeyes/config/locale/bn_IN/LC_MESSAGES/safeeyes.po
safeeyes/config/locale/ca/LC_MESSAGES/safeeyes.mo
safeeyes/config/locale/ca/LC_MESSAGES/safeeyes.po
safeeyes/config/locale/cs/LC_MESSAGES/safeeyes.mo
safeeyes/config/locale/cs/LC_MESSAGES/safeeyes.po
safeeyes/config/locale/da/LC_MESSAGES/safeeyes.mo
safeeyes/config/locale/da/LC_MESSAGES/safeeyes.po
safeeyes/config/locale/de/LC_MESSAGES/safeeyes.mo
safeeyes/config/locale/de/LC_MESSAGES/safeeyes.po
safeeyes/config/locale/eo/LC_MESSAGES/safeeyes.mo
safeeyes/config/locale/eo/LC_MESSAGES/safeeyes.po
safeeyes/config/locale/es/LC_MESSAGES/safeeyes.mo
safeeyes/config/locale/es/LC_MESSAGES/safeeyes.po
safeeyes/config/locale/et/LC_MESSAGES/safeeyes.mo
safeeyes/config/locale/et/LC_MESSAGES/safeeyes.po
safeeyes/config/locale/eu/LC_MESSAGES/safeeyes.mo
safeeyes/config/locale/eu/LC_MESSAGES/safeeyes.po
safeeyes/config/locale/fa/LC_MESSAGES/safeeyes.mo
safeeyes/config/locale/fa/LC_MESSAGES/safeeyes.po
safeeyes/config/locale/fi/LC_MESSAGES/safeeyes.po
safeeyes/config/locale/fr/LC_MESSAGES/safeeyes.mo
safeeyes/config/locale/fr/LC_MESSAGES/safeeyes.po
safeeyes/config/locale/he/LC_MESSAGES/safeeyes.mo
safeeyes/config/locale/he/LC_MESSAGES/safeeyes.po
safeeyes/config/locale/hi/LC_MESSAGES/safeeyes.mo
safeeyes/config/locale/hi/LC_MESSAGES/safeeyes.po
safeeyes/config/locale/hu/LC_MESSAGES/safeeyes.mo
safeeyes-3.3.1.dist-info/licenses/LICENSE
safeeyes-3.3.1.dist-info/METADATA
safeeyes-3.3.1.dist-info/WHEEL
safeeyes-3.3.1.dist-info/entry_points.txt
safeeyes-3.3.1.dist-info/top_level.txt
safeeyes-3.3.1.dist-info/RECORD
