Metadata-Version: 2.4
Name: safeeyes
Version: 3.3.1
Summary: Protect your eyes from eye strain using this continuous breaks reminder.
Author-email: Gobinath Loganathan <slgobinath@gmail.com>
License: GPL-3.0-or-later
Project-URL: Homepage, https://github.com/slgobinath/safeeyes
Project-URL: Downloads, https://github.com/slgobinath/safeeyes/archive/v3.3.1.tar.gz
Keywords: linux utility health eye-strain safe-eyes
Classifier: Development Status :: 5 - Production/Stable
Classifier: Environment :: X11 Applications :: GTK
Classifier: Environment :: Other Environment
Classifier: Intended Audience :: End Users/Desktop
Classifier: Operating System :: POSIX :: Linux
Classifier: Programming Language :: Python :: 3
Classifier: Programming Language :: Python :: 3.10
Classifier: Programming Language :: Python :: 3.11
Classifier: Programming Language :: Python :: 3.12
Classifier: Topic :: Utilities
Requires-Python: >=3.10
License-File: LICENSE
Requires-Dist: PyGObject
Requires-Dist: babel
Requires-Dist: packaging
Requires-Dist: python-xlib
Provides-Extra: healthstats
Requires-Dist: croniter; extra == "healthstats"
Provides-Extra: wayland
Requires-Dist: pywayland; extra == "wayland"
Dynamic: license-file
